krutils/AppErr.py
krutils/CONST.py
krutils/__init__.py
krutils/_dbmgr.py
krutils/futils.py
krutils/logger.py
krutils/logger2.py
krutils/utils.py
krutils-0.20230707.1702.dist-info/METADATA
krutils-0.20230707.1702.dist-info/WHEEL
krutils-0.20230707.1702.dist-info/top_level.txt
krutils-0.20230707.1702.dist-info/RECORD
